README.md
hi_tea.py
setup.py
teaa.egg-info/PKG-INFO
teaa.egg-info/SOURCES.txt
teaa.egg-info/dependency_links.txt
teaa.egg-info/entry_points.txt
teaa.egg-info/requires.txt
teaa.egg-info/top_level.txt