Metadata-Version: 2.1
Name: teaa
Version: 0.0.1
Summary: A simple package for https://app.tea.xyz/. Example tea-xyz1 - https://github.com/madest92/tea-xyz1 and tea-xyz2 - https://github.com/madest92/tea-xyz2
Home-page: https://github.com/CryptoGu1/teaa.git
Author: CryptoGu1
Author-email: Kriptoairdrop9@gmail.com
Project-URL: Homepage, https://github.com/CryptoGu1/teaa.git
Project-URL: Source, https://github.com/CryptoGu1/teaa.git
Classifier: License :: OSI Approved :: MIT License
Classifier: Programming Language :: Python :: 3
Requires-Python: >=3.6
Requires-Dist: teaa1
Requires-Dist: teaa2
